imgsteg/__init__.py
imgsteg/imgsteg.py
imgsteg-1.0.3.dist-info/METADATA
imgsteg-1.0.3.dist-info/WHEEL
imgsteg-1.0.3.dist-info/top_level.txt
imgsteg-1.0.3.dist-info/RECORD
