Metadata-Version: 2.1
Name: imgsteg
Version: 1.0.3
Summary: python library for image steganography. used to encrypt and decrypt text message inside an image
Home-page: https://sujaid.pythonanywhere.com
Author-email: sujaidsujaid1162@gmail.com
License: MTL
Keywords: image steganography,steganography,image,sujaid
Classifier: Programming Language :: Python :: 3
Classifier: License :: OSI Approved :: MIT License
Requires-Dist: numpy
Requires-Dist: Pillow
